wikireader/__init__.py
wikireader/cli.py
wikireader/dmenu.py
wikireader/main.py
wikireader/browser/__init__.py
wikireader/browser/browser.py
wikireader/config/__init__.py
wikireader/config/config.py
wikireader/config/data/__init__.py
wikireader/config/data/config.json
wikireader/config/data/dark.css
wikireader/config/data/light.css
wikireader/html_convert/__init__.py
wikireader/html_convert/css.py
wikireader/html_convert/page.py
wikireader/html_convert/page_template.py
wikireader/html_convert/text2html.py
wikireader/wiki/__init__.py
wikireader/wiki/mine_wiki.py
wikireader-0.0.5.dist-info/LICENSE
wikireader-0.0.5.dist-info/METADATA
wikireader-0.0.5.dist-info/WHEEL
wikireader-0.0.5.dist-info/entry_points.txt
wikireader-0.0.5.dist-info/top_level.txt
wikireader-0.0.5.dist-info/RECORD
