Metadata-Version: 2.1
Name: wikireader
Version: 0.0.5
Summary: Read wikipedia articles distraction free
Home-page: https://github.com/mke21/wikireader
Author: Marcel Kerkveld
License: UNKNOWN
Platform: UNKNOWN
Classifier: Development Status :: 3 - Alpha
Classifier: License :: OSI Approved :: MIT License
Classifier: Programming Language :: Python :: 3.8
Requires-Dist: PyQt5 (>=5.15.1)
Requires-Dist: PyQtWebEngine (>=5.15.1)
Requires-Dist: wikipedia (>=1.4.0)
